open_medical/__init__.py
open_medical/main.py
Open_Medical-0.0.1.dist-info/METADATA
Open_Medical-0.0.1.dist-info/WHEEL
Open_Medical-0.0.1.dist-info/top_level.txt
Open_Medical-0.0.1.dist-info/RECORD
