Metadata-Version: 2.1
Name: Open-Medical
Version: 0.0.1
Summary: Given a query this project downloads articles from PubMed website and then do the following analysis: Summarization, Knowledge Grapg, NER, Topic Modeling
Home-page: UNKNOWN
Author: Mehdi Hosseini Moghadam
Author-email: <m.h.moghadam1996@gmail.com>
License: UNKNOWN
Keywords: PubMed,NLP,BioMedical,Biology,Summarization,BioMedical Summarization,Knowledge Graph,NER,Topic Modeling
Platform: UNKNOWN
Classifier: Development Status :: 1 - Planning
Classifier: Intended Audience :: Developers
Classifier: Programming Language :: Python :: 3
Classifier: Operating System :: Unix
Classifier: Operating System :: MacOS :: MacOS X
Classifier: Operating System :: Microsoft :: Windows
Requires-Dist: bert-extractive-summarizer
Requires-Dist: sacremoses
Requires-Dist: pyvis
Requires-Dist: awscli
Requires-Dist: wikipedia-api
Requires-Dist: neuralcoref
Requires-Dist: transformers
Requires-Dist: pymed
Requires-Dist: pyLDAvis
